pyannotations/__init__.py
pyannotations/annotations.py
pyannotations-0.0.4.dist-info/LICENSE
pyannotations-0.0.4.dist-info/METADATA
pyannotations-0.0.4.dist-info/WHEEL
pyannotations-0.0.4.dist-info/top_level.txt
pyannotations-0.0.4.dist-info/RECORD
